datasette_remote_metadata/__init__.py
datasette_remote_metadata-0.1.dist-info/METADATA
datasette_remote_metadata-0.1.dist-info/WHEEL
datasette_remote_metadata-0.1.dist-info/entry_points.txt
datasette_remote_metadata-0.1.dist-info/top_level.txt
datasette_remote_metadata-0.1.dist-info/RECORD
