Metadata-Version: 2.1
Name: datasette-remote-metadata
Version: 0.1
Summary: Periodically refresh Datasette metadata from a remote URL
Home-page: https://github.com/simonw/datasette-remote-metadata
Author: Simon Willison
License: Apache License, Version 2.0
Project-URL: Issues, https://github.com/simonw/datasette-remote-metadata/issues
Project-URL: CI, https://github.com/simonw/datasette-remote-metadata/actions
Project-URL: Changelog, https://github.com/simonw/datasette-remote-metadata/releases
Platform: UNKNOWN
Requires-Python: >=3.6
Requires-Dist: datasette
Provides-Extra: test
Requires-Dist: pytest ; extra == 'test'
Requires-Dist: pytest-asyncio ; extra == 'test'
Requires-Dist: pytest-httpx ; extra == 'test'
